pathpy/__init__.py
pathpy/algorithms/__init__.py
pathpy/algorithms/centralities.py
pathpy/algorithms/components.py
pathpy/algorithms/infomap.py
pathpy/algorithms/modularity.py
pathpy/algorithms/path_measures.py
pathpy/algorithms/random_graphs.py
pathpy/algorithms/random_walk.py
pathpy/algorithms/shortest_paths.py
pathpy/algorithms/spectral.py
pathpy/algorithms/statistics.py
pathpy/algorithms/temporal_walk.py
pathpy/classes/__init__.py
pathpy/classes/dag.py
pathpy/classes/higher_order_network.py
pathpy/classes/markov_sequence.py
pathpy/classes/multi_order_model.py
pathpy/classes/network.py
pathpy/classes/paths.py
pathpy/classes/rolling_time_window.py
pathpy/classes/temporal_network.py
pathpy/path_extraction/__init__.py
pathpy/path_extraction/dag_paths.py
pathpy/path_extraction/origin_destination_stats.py
pathpy/path_extraction/random_walk.py
pathpy/path_extraction/temporal_paths.py
pathpy/utils/__init__.py
pathpy/utils/default_containers.py
pathpy/utils/exceptions.py
pathpy/utils/log.py
pathpy/visualisation/__init__.py
pathpy/visualisation/alluvial.py
pathpy/visualisation/html.py
pathpy/visualisation/pdf.py
pathpy/visualisation/tikz.py
pathpy/visualisation_assets/d3.v4.min.js
pathpy/visualisation_assets/diffusion_template.html
pathpy/visualisation_assets/network_template.html
pathpy/visualisation_assets/paths_template.html
pathpy/visualisation_assets/tempnet_template.html
pathpy/visualisation_assets/walk_template.html
tests/__init__.py
tests/conftest.py
tests/test_DAG.py
tests/test_HigherOrderNetwork.py
tests/test_MultiOrderModel.py
tests/test_Network.py
tests/test_OriginDestinationPaths.py
tests/test_Path.py
tests/test_TemporalNetwork.py
tests/test_centralities.py
tests/test_estimation.py
tests/test_random_graphs.py
tests/test_spectral.py
pathpy2-2.2.0.dist-info/LICENSE.txt
pathpy2-2.2.0.dist-info/METADATA
pathpy2-2.2.0.dist-info/WHEEL
pathpy2-2.2.0.dist-info/top_level.txt
pathpy2-2.2.0.dist-info/RECORD
